lisf.py
lisf-0.1.6.dist-info/METADATA
lisf-0.1.6.dist-info/WHEEL
lisf-0.1.6.dist-info/RECORD
